README.md
setup.cfg
setup.py
moduml/__init__.py
moduml/__main__.py
moduml/core.py
moduml/graph_viz_builder.py
moduml/layout_types.py
moduml.egg-info/PKG-INFO
moduml.egg-info/SOURCES.txt
moduml.egg-info/dependency_links.txt
moduml.egg-info/entry_points.txt
moduml.egg-info/requires.txt
moduml.egg-info/top_level.txt
moduml/module/__init__.py
moduml/module/imports.py
moduml/module/interface.py
moduml/network/__init__.py
moduml/network/creator.py
moduml/network/filtering.py
moduml/network/utils.py