Metadata-Version: 1.1
Name: moduml
Version: 0.2.0
Summary: UML-inspired diagrams of python modules and packages.
Home-page: https://github.com/roschly/moduml
Author: roschly
Author-email: UNKNOWN
License: UNKNOWN
Download-URL: https://github.com/roschly/moduml/archive/refs/tags/v0.1.1.tar.gz
Platform: UNKNOWN
